{
    "boxShadow": "none",
    "iconSVG": "/static/media/icon.f2c34197dbcf03595098986de898928f.svg",
    "topRow": 53,
    "labelWidth": 5,
    "type": "INPUT_WIDGET_V2",
    "animateLoading": false,
    "resetOnSubmit": true,
    "leftColumn": 1,
    "dynamicBindingPathList": [
        {"key": "accentColor"},
        {"key": "borderRadius"},
        {"key": "defaultText"}
    ],
    "labelStyle": "",
    "inputType": "MULTI_LINE_TEXT",
    "isDisabled": false,
    "isRequired": false,
    "dynamicHeight": "AUTO_HEIGHT",
    "accentColor": "{{appsmith.theme.colors.primaryColor}}",
    "showStepArrows": false,
    "isVisible": true,
    "version": 2,
    "tags": ["数据录入-输入器组件"],
    "isLoading": false,
    "borderRadius": "{{appsmith.theme.borderRadius.appBorderRadius}}",
    "originalBottomRow": 63,
    "mobileBottomRow": 60,
    "widgetName": "Input2",
    "displayName": "输入框",
    "searchTags": [
        "form",
        "text input",
        "number",
        "textarea"
    ],
    "bottomRow": 64,
    "parentRowSpace": 10,
    "autoFocus": false,
    "hideCard": false,
    "mobileRightColumn": 18,
    "parentColumnSpace": 21.0625,
    "dynamicTriggerPathList": [],
    "labelPosition": "Top",
    "key": "1dvfi6szvh",
    "labelTextSize": "0.875rem",
    "isDeprecated": false,
    "rightColumn": 62,
    "widgetId": "aajtrjncgy",
    "minWidth": 450,
    "label": "delete_script",
    "parentId": "brb8mb63rk",
    "labelAlignment": "left",
    "renderMode": "CANVAS",
    "mobileTopRow": 53,
    "responsiveBehavior": "fill",
    "originalTopRow": 53,
    "mobileLeftColumn": 0,
    "maxDynamicHeight": 9000,
    "shouldAllowAutofill": false,
    "iconAlign": "left",
    "defaultText": "{{sript_getbyid.data[0].delete_script}}",
    "minDynamicHeight": 4
}